astro_seeing-1.2.dist-info/licenses/LICENSE
seeing/__init__.py
seeing/_version.py
seeing/formulary.py
seeing/integrator.py
seeing/lambdifyDictionaries.py
seeing/lambdifyDictionariesGPU.py
seeing/sympyHelpers.py
astro_seeing-1.2.dist-info/METADATA
astro_seeing-1.2.dist-info/WHEEL
astro_seeing-1.2.dist-info/top_level.txt
astro_seeing-1.2.dist-info/RECORD
