Metadata-Version: 2.4
Name: astro-seeing
Version: 1.2
Summary: Sympy Expressions Evaluation Implemented oN the GPU
Author-email: Fabio Rossi <fabio.rossi@inaf.it>
License: MIT License
Project-URL: repository, https://github.com/astro-tiptop/SEEING
Requires-Python: >=3.7
License-File: LICENSE
Requires-Dist: matplotlib
Requires-Dist: numpy
Requires-Dist: scipy
Requires-Dist: sympy
Provides-Extra: gpu
Requires-Dist: cupy; extra == "gpu"
Dynamic: license-file
